geometry_tools/__init__.py
geometry_tools/geometry_tools.py
neuromorpho-0.0.3.data/scripts/neuromorpho
rest_wrapper/__init__.py
rest_wrapper/rest_wrapper.py
neuromorpho-0.0.3.dist-info/LICENSE
neuromorpho-0.0.3.dist-info/METADATA
neuromorpho-0.0.3.dist-info/WHEEL
neuromorpho-0.0.3.dist-info/top_level.txt
neuromorpho-0.0.3.dist-info/RECORD
