Metadata-Version: 2.1
Name: neuromorpho
Version: 0.0.3
Summary: Query NeuroMorpho.org database via REST
Home-page: https://github.com/NeuroBox3D/neuromorpho
Author: Stephan Grein
Author-email: stephan@syntaktischer-zucker.de
Classifier: Programming Language :: Python :: 3
Classifier: License :: OSI Approved :: MIT License
Classifier: Operating System :: OS Independent
License-File: LICENSE
